qt_generic_utils/__init__.py
qt_generic_utils/about_dialog.py
qt_generic_utils/license_dialog.py
qt_generic_utils/messaging.py
qt_generic_utils-0.1.0.dist-info/METADATA
qt_generic_utils-0.1.0.dist-info/WHEEL
qt_generic_utils-0.1.0.dist-info/RECORD
