Metadata-Version: 2.1
Name: qt-generic-utils
Version: 0.1.0
Summary: 
Author: floris vernieuwe
Author-email: floris@vernieuwe.eu
Requires-Python: >=3.10,<3.12
Classifier: Programming Language :: Python :: 3
Classifier: Programming Language :: Python :: 3.10
Classifier: Programming Language :: Python :: 3.11
Requires-Dist: poetry-dynamic-versioning (>=1.1.1,<2.0.0)
Requires-Dist: pydantic (>=2.4.2,<3.0.0)
Requires-Dist: qtpy (>=2.4.1,<3.0.0)
